llama_index/readers/weaviate/__init__.py
llama_index/readers/weaviate/base.py
llama_index_readers_weaviate-0.4.1.dist-info/METADATA
llama_index_readers_weaviate-0.4.1.dist-info/WHEEL
llama_index_readers_weaviate-0.4.1.dist-info/licenses/LICENSE
llama_index_readers_weaviate-0.4.1.dist-info/RECORD
