Metadata-Version: 2.4
Name: llama-index-readers-weaviate
Version: 0.4.1
Summary: llama-index readers weaviate integration
Author-email: Your Name <you@example.com>
Maintainer: jerryjliu
License-Expression: MIT
License-File: LICENSE
Requires-Python: <4.0,>=3.9
Requires-Dist: llama-index-core<0.15,>=0.13.0
Requires-Dist: weaviate-client<4,>=3.26.2
